skillgen/__init__.py
skillgen/__main__.py
skillgen/cli.py
skillgen/config.py
skillgen/converter.py
skillgen/fetcher.py
skillgen/generator.py
skillgen/indexer.py
skillgen/installer.py
skillgen/keywords.py
skillgen/models.py
skillgen/parser.py
skillgen/util.py
skillgen-0.1.0.dist-info/licenses/LICENSE
skillgen-0.1.0.dist-info/METADATA
skillgen-0.1.0.dist-info/WHEEL
skillgen-0.1.0.dist-info/entry_points.txt
skillgen-0.1.0.dist-info/top_level.txt
skillgen-0.1.0.dist-info/RECORD
