Metadata-Version: 2.4
Name: skillgen
Version: 0.1.0
Summary: Generate Agent Skills from llms.txt
Author: Mihir Srivastava
License: MIT License
Keywords: llms.txt,agent,skills,documentation,generator
Classifier: Programming Language :: Python :: 3
Classifier: License :: OSI Approved :: MIT License
Classifier: Operating System :: OS Independent
Requires-Python: >=3.9
License-File: LICENSE
Requires-Dist: requests>=2.31.0
Requires-Dist: PyYAML>=6.0
Requires-Dist: trafilatura>=1.8.0
Requires-Dist: beautifulsoup4>=4.12.0
Requires-Dist: transformers>=4.44.0
Requires-Dist: torch>=2.1.0
Provides-Extra: extras
Requires-Dist: markdownify>=0.11.6; extra == "extras"
Provides-Extra: llm
Requires-Dist: transformers>=4.44.0; extra == "llm"
Requires-Dist: torch>=2.1.0; extra == "llm"
Provides-Extra: test
Requires-Dist: pytest>=7.4; extra == "test"
Dynamic: license-file
